commons/__init__.py
commons/base.py
commons/dict.py
commons/round.py
commons/structures.py
commons_py-0.2.1.dist-info/top_level.txt
commons_py-0.2.1.dist-info/METADATA
commons_py-0.2.1.dist-info/DESCRIPTION.rst
commons_py-0.2.1.dist-info/metadata.json
commons_py-0.2.1.dist-info/WHEEL
commons_py-0.2.1.dist-info/RECORD
